example/__init__.py
example/main.py
exampleabacaba/__init__.py
exampleabacaba/main.py
pyexample54321/__init__.py
pyexample54321/main.py
pyexample54321-0.1.3.dist-info/METADATA
pyexample54321-0.1.3.dist-info/WHEEL
pyexample54321-0.1.3.dist-info/top_level.txt
pyexample54321-0.1.3.dist-info/RECORD
