Metadata-Version: 2.1
Name: pyexample54321
Version: 0.1.3
Summary: A pyexample54321 Python package
Home-page: UNKNOWN
Author: Stephen Hudson
Author-email: shudson@anl.gov
License: BSD 2-clause
Platform: UNKNOWN
Classifier: Development Status :: 1 - Planning
Classifier: Intended Audience :: Science/Research
Classifier: License :: OSI Approved :: BSD License
Classifier: Operating System :: POSIX :: Linux
Classifier: Programming Language :: Python :: 2
Classifier: Programming Language :: Python :: 2.7
Classifier: Programming Language :: Python :: 3
Classifier: Programming Language :: Python :: 3.4
Classifier: Programming Language :: Python :: 3.5
Requires-Dist: numpy (>=1.20)
